ndx_whisk/__init__.py
ndx_whisk/spec/ndx-whisk.extensions.yaml
ndx_whisk/spec/ndx-whisk.namespace.yaml
ndx_whisk-0.1.1.dist-info/LICENSE.txt
ndx_whisk-0.1.1.dist-info/METADATA
ndx_whisk-0.1.1.dist-info/WHEEL
ndx_whisk-0.1.1.dist-info/top_level.txt
ndx_whisk-0.1.1.dist-info/RECORD
