Metadata-Version: 2.1
Name: ndx-whisk
Version: 0.1.1
Summary: NWB extension to store whisker tracking measurements computed with Whisk (Janelia Whisker Tracker) or other video-based whisker tracking methods.
Home-page: 
Author: Vincent Prevosto
Author-email: prevosto@mit.edu
License: BSD-3
Keywords: NeurodataWithoutBorders,NWB,nwb-extension,ndx-extension
Classifier: Intended Audience :: Developers
Classifier: Intended Audience :: Science/Research
Classifier: License :: OSI Approved :: BSD License
License-File: LICENSE.txt
Requires-Dist: pynwb (<3,>=1.5.0)
Requires-Dist: hdmf (<4,>=2.5.6)
Requires-Dist: WhiskiWrap
